[
  {
    "id": 1,
    "iso1": "AF",
    "pays_fr": "Afghanistan",
    "pays_en": "Afghanistan"
  },
  {
    "id": 2,
    "iso1": "AL",
    "pays_fr": "Albanie",
    "pays_en": "Albania"
  },
  {
    "id": 3,
    "iso1": "AQ",
    "pays_fr": "Antarctique",
    "pays_en": "Antarctica"
  },
  {
    "id": 4,
    "iso1": "DZ",
    "pays_fr": "Algérie",
    "pays_en": "Algeria"
  },
  {
    "id": 5,
    "iso1": "AS",
    "pays_fr": "Samoa Américaines",
    "pays_en": "American Samoa"
  },
  {
    "id": 6,
    "iso1": "AD",
    "pays_fr": "Andorre",
    "pays_en": "Andorra"
  },
  {
    "id": 7,
    "iso1": "AO",
    "pays_fr": "Angola",
    "pays_en": "Angola"
  },
  {
    "id": 8,
    "iso1": "AG",
    "pays_fr": "Antigua-et-Barbuda",
    "pays_en": "Antigua and Barbuda"
  },
  {
    "id": 9,
    "iso1": "AZ",
    "pays_fr": "Azerbaïdjan",
    "pays_en": "Azerbaijan"
  },
  {
    "id": 10,
    "iso1": "AR",
    "pays_fr": "Argentine",
    "pays_en": "Argentina"
  },
  {
    "id": 11,
    "iso1": "AU",
    "pays_fr": "Australie",
    "pays_en": "Australia"
  },
  {
    "id": 12,
    "iso1": "AT",
    "pays_fr": "Autriche",
    "pays_en": "Austria"
  },
  {
    "id": 13,
    "iso1": "BS",
    "pays_fr": "Bahamas",
    "pays_en": "Bahamas"
  },
  {
    "id": 14,
    "iso1": "BH",
    "pays_fr": "Bahreïn",
    "pays_en": "Bahrain"
  },
  {
    "id": 15,
    "iso1": "BD",
    "pays_fr": "Bangladesh",
    "pays_en": "Bangladesh"
  },
  {
    "id": 16,
    "iso1": "AM",
    "pays_fr": "Arménie",
    "pays_en": "Armenia"
  },
  {
    "id": 17,
    "iso1": "BB",
    "pays_fr": "Barbade",
    "pays_en": "Barbados"
  },
  {
    "id": 18,
    "iso1": "BE",
    "pays_fr": "Belgique",
    "pays_en": "Belgium"
  },
  {
    "id": 19,
    "iso1": "BM",
    "pays_fr": "Bermudes",
    "pays_en": "Bermuda"
  },
  {
    "id": 20,
    "iso1": "BT",
    "pays_fr": "Bhoutan",
    "pays_en": "Bhutan"
  },
  {
    "id": 21,
    "iso1": "BO",
    "pays_fr": "Bolivie",
    "pays_en": "Bolivia"
  },
  {
    "id": 22,
    "iso1": "BA",
    "pays_fr": "Bosnie-Herzégovine",
    "pays_en": "Bosnia and Herzegovina"
  },
  {
    "id": 23,
    "iso1": "BW",
    "pays_fr": "Botswana",
    "pays_en": "Botswana"
  },
  {
    "id": 24,
    "iso1": "BV",
    "pays_fr": "Île Bouvet",
    "pays_en": "Bouvet Island"
  },
  {
    "id": 25,
    "iso1": "BR",
    "pays_fr": "Brésil",
    "pays_en": "Brazil"
  },
  {
    "id": 26,
    "iso1": "BZ",
    "pays_fr": "Belize",
    "pays_en": "Belize"
  },
  {
    "id": 27,
    "iso1": "IO",
    "pays_fr": "Territoire Britannique de l'Océan Indien",
    "pays_en": "British Indian Ocean Territory"
  },
  {
    "id": 28,
    "iso1": "SB",
    "pays_fr": "Îles Salomon",
    "pays_en": "Solomon Islands"
  },
  {
    "id": 29,
    "iso1": "VG",
    "pays_fr": "Îles Vierges Britanniques",
    "pays_en": "British Virgin Islands"
  },
  {
    "id": 30,
    "iso1": "BN",
    "pays_fr": "Brunéi Darussalam",
    "pays_en": "Brunei Darussalam"
  },
  {
    "id": 31,
    "iso1": "BG",
    "pays_fr": "Bulgarie",
    "pays_en": "Bulgaria"
  },
  {
    "id": 32,
    "iso1": "MM",
    "pays_fr": "Myanmar",
    "pays_en": "Myanmar"
  },
  {
    "id": 33,
    "iso1": "BI",
    "pays_fr": "Burundi",
    "pays_en": "Burundi"
  },
  {
    "id": 34,
    "iso1": "BY",
    "pays_fr": "Bélarus",
    "pays_en": "Belarus"
  },
  {
    "id": 35,
    "iso1": "KH",
    "pays_fr": "Cambodge",
    "pays_en": "Cambodia"
  },
  {
    "id": 36,
    "iso1": "CM",
    "pays_fr": "Cameroun",
    "pays_en": "Cameroon"
  },
  {
    "id": 37,
    "iso1": "CA",
    "pays_fr": "Canada",
    "pays_en": "Canada"
  },
  {
    "id": 38,
    "iso1": "CV",
    "pays_fr": "Cap-vert",
    "pays_en": "Cape Verde"
  },
  {
    "id": 39,
    "iso1": "KY",
    "pays_fr": "Îles Caïmanes",
    "pays_en": "Cayman Islands"
  },
  {
    "id": 40,
    "iso1": "CF",
    "pays_fr": "République Centrafricaine",
    "pays_en": "Central African"
  },
  {
    "id": 41,
    "iso1": "LK",
    "pays_fr": "Sri Lanka",
    "pays_en": "Sri Lanka"
  },
  {
    "id": 42,
    "iso1": "TD",
    "pays_fr": "Tchad",
    "pays_en": "Chad"
  },
  {
    "id": 43,
    "iso1": "CL",
    "pays_fr": "Chili",
    "pays_en": "Chile"
  },
  {
    "id": 44,
    "iso1": "CN",
    "pays_fr": "Chine",
    "pays_en": "China"
  },
  {
    "id": 45,
    "iso1": "TW",
    "pays_fr": "Taïwan",
    "pays_en": "Taiwan"
  },
  {
    "id": 46,
    "iso1": "CX",
    "pays_fr": "Île Christmas",
    "pays_en": "Christmas Island"
  },
  {
    "id": 47,
    "iso1": "CC",
    "pays_fr": "Îles Cocos (Keeling)",
    "pays_en": "Cocos (Keeling) Islands"
  },
  {
    "id": 48,
    "iso1": "CO",
    "pays_fr": "Colombie",
    "pays_en": "Colombia"
  },
  {
    "id": 49,
    "iso1": "KM",
    "pays_fr": "Comores",
    "pays_en": "Comoros"
  },
  {
    "id": 50,
    "iso1": "YT",
    "pays_fr": "Mayotte",
    "pays_en": "Mayotte"
  },
  {
    "id": 51,
    "iso1": "CG",
    "pays_fr": "République du Congo",
    "pays_en": "Republic of the Congo"
  },
  {
    "id": 52,
    "iso1": "CD",
    "pays_fr": "Zaïre",
    "pays_en": "The Democratic Republic Of The Congo"
  },
  {
    "id": 53,
    "iso1": "CK",
    "pays_fr": "Îles Cook",
    "pays_en": "Cook Islands"
  },
  {
    "id": 54,
    "iso1": "CR",
    "pays_fr": "Costa Rica",
    "pays_en": "Costa Rica"
  },
  {
    "id": 55,
    "iso1": "HR",
    "pays_fr": "Croatie",
    "pays_en": "Croatia"
  },
  {
    "id": 56,
    "iso1": "CU",
    "pays_fr": "Cuba",
    "pays_en": "Cuba"
  },
  {
    "id": 57,
    "iso1": "CY",
    "pays_fr": "Chypre",
    "pays_en": "Cyprus"
  },
  {
    "id": 58,
    "iso1": "CZ",
    "pays_fr": "République Tchèque",
    "pays_en": "Czech Republic"
  },
  {
    "id": 59,
    "iso1": "BJ",
    "pays_fr": "Bénin",
    "pays_en": "Benin"
  },
  {
    "id": 60,
    "iso1": "DK",
    "pays_fr": "Danemark",
    "pays_en": "Denmark"
  },
  {
    "id": 61,
    "iso1": "DM",
    "pays_fr": "Dominique",
    "pays_en": "Dominica"
  },
  {
    "id": 62,
    "iso1": "DO",
    "pays_fr": "République Dominicaine",
    "pays_en": "Dominican Republic"
  },
  {
    "id": 63,
    "iso1": "EC",
    "pays_fr": "Équateur",
    "pays_en": "Ecuador"
  },
  {
    "id": 64,
    "iso1": "SV",
    "pays_fr": "Salvador",
    "pays_en": "El Salvador"
  },
  {
    "id": 65,
    "iso1": "GQ",
    "pays_fr": "Guinée Équatoriale",
    "pays_en": "Equatorial Guinea"
  },
  {
    "id": 66,
    "iso1": "ET",
    "pays_fr": "Éthiopie",
    "pays_en": "Ethiopia"
  },
  {
    "id": 67,
    "iso1": "ER",
    "pays_fr": "Érythrée",
    "pays_en": "Eritrea"
  },
  {
    "id": 68,
    "iso1": "EE",
    "pays_fr": "Estonie",
    "pays_en": "Estonia"
  },
  {
    "id": 69,
    "iso1": "FO",
    "pays_fr": "Îles Féroé",
    "pays_en": "Faroe Islands"
  },
  {
    "id": 70,
    "iso1": "FK",
    "pays_fr": "Îles (malvinas) Falkland",
    "pays_en": "Falkland Islands"
  },
  {
    "id": 71,
    "iso1": "GS",
    "pays_fr": "Géorgie du Sud et les Îles Sandwich du Sud",
    "pays_en": "South Georgia and the South Sandwich Islands"
  },
  {
    "id": 72,
    "iso1": "FJ",
    "pays_fr": "Fidji",
    "pays_en": "Fiji"
  },
  {
    "id": 73,
    "iso1": "FI",
    "pays_fr": "Finlande",
    "pays_en": "Finland"
  },
  {
    "id": 74,
    "iso1": "AX",
    "pays_fr": "Îles Åland",
    "pays_en": "Åland Islands"
  },
  {
    "id": 75,
    "iso1": "FR",
    "pays_fr": "France",
    "pays_en": "France"
  },
  {
    "id": 76,
    "iso1": "GF",
    "pays_fr": "Guyane Française",
    "pays_en": "French Guiana"
  },
  {
    "id": 77,
    "iso1": "PF",
    "pays_fr": "Polynésie Française",
    "pays_en": "French Polynesia"
  },
  {
    "id": 78,
    "iso1": "TF",
    "pays_fr": "Terres Australes Françaises",
    "pays_en": "French Southern Territories"
  },
  {
    "id": 79,
    "iso1": "DJ",
    "pays_fr": "Djibouti",
    "pays_en": "Djibouti"
  },
  {
    "id": 80,
    "iso1": "GA",
    "pays_fr": "Gabon",
    "pays_en": "Gabon"
  },
  {
    "id": 81,
    "iso1": "GE",
    "pays_fr": "Géorgie",
    "pays_en": "Georgia"
  },
  {
    "id": 82,
    "iso1": "GM",
    "pays_fr": "Gambie",
    "pays_en": "Gambia"
  },
  {
    "id": 83,
    "iso1": "PS",
    "pays_fr": "Territoire Palestinien Occupé",
    "pays_en": "Occupied Palestinian Territory"
  },
  {
    "id": 84,
    "iso1": "DE",
    "pays_fr": "Allemagne",
    "pays_en": "Germany"
  },
  {
    "id": 85,
    "iso1": "GH",
    "pays_fr": "Ghana",
    "pays_en": "Ghana"
  },
  {
    "id": 86,
    "iso1": "GI",
    "pays_fr": "Gibraltar",
    "pays_en": "Gibraltar"
  },
  {
    "id": 87,
    "iso1": "KI",
    "pays_fr": "Kiribati",
    "pays_en": "Kiribati"
  },
  {
    "id": 88,
    "iso1": "GR",
    "pays_fr": "Grèce",
    "pays_en": "Greece"
  },
  {
    "id": 89,
    "iso1": "GL",
    "pays_fr": "Groenland",
    "pays_en": "Greenland"
  },
  {
    "id": 90,
    "iso1": "GD",
    "pays_fr": "Grenade",
    "pays_en": "Grenada"
  },
  {
    "id": 91,
    "iso1": "GP",
    "pays_fr": "Guadeloupe",
    "pays_en": "Guadeloupe"
  },
  {
    "id": 92,
    "iso1": "GU",
    "pays_fr": "Guam",
    "pays_en": "Guam"
  },
  {
    "id": 93,
    "iso1": "GT",
    "pays_fr": "Guatemala",
    "pays_en": "Guatemala"
  },
  {
    "id": 94,
    "iso1": "GN",
    "pays_fr": "Guinée",
    "pays_en": "Guinea"
  },
  {
    "id": 95,
    "iso1": "GY",
    "pays_fr": "Guyana",
    "pays_en": "Guyana"
  },
  {
    "id": 96,
    "iso1": "HT",
    "pays_fr": "Haïti",
    "pays_en": "Haiti"
  },
  {
    "id": 97,
    "iso1": "HM",
    "pays_fr": "Îles Heard et Mcdonald",
    "pays_en": "Heard Island and McDonald Islands"
  },
  {
    "id": 98,
    "iso1": "VA",
    "pays_fr": "Saint-Siège (état de la Cité du Vatican)",
    "pays_en": "Vatican City State"
  },
  {
    "id": 99,
    "iso1": "HN",
    "pays_fr": "Honduras",
    "pays_en": "Honduras"
  },
  {
    "id": 100,
    "iso1": "HK",
    "pays_fr": "Hong-Kong",
    "pays_en": "Hong Kong"
  },
  {
    "id": 101,
    "iso1": "HU",
    "pays_fr": "Hongrie",
    "pays_en": "Hungary"
  },
  {
    "id": 102,
    "iso1": "IS",
    "pays_fr": "Islande",
    "pays_en": "Iceland"
  },
  {
    "id": 103,
    "iso1": "IN",
    "pays_fr": "Inde",
    "pays_en": "India"
  },
  {
    "id": 104,
    "iso1": "ID",
    "pays_fr": "Indonésie",
    "pays_en": "Indonesia"
  },
  {
    "id": 105,
    "iso1": "IR",
    "pays_fr": "Iran",
    "pays_en": "Islamic Republic of Iran"
  },
  {
    "id": 106,
    "iso1": "IQ",
    "pays_fr": "Irak",
    "pays_en": "Iraq"
  },
  {
    "id": 107,
    "iso1": "IE",
    "pays_fr": "Irlande",
    "pays_en": "Ireland"
  },
  {
    "id": 108,
    "iso1": "IL",
    "pays_fr": "Israël",
    "pays_en": "Israel"
  },
  {
    "id": 109,
    "iso1": "IT",
    "pays_fr": "Italie",
    "pays_en": "Italy"
  },
  {
    "id": 110,
    "iso1": "CI",
    "pays_fr": "Côte d'Ivoire",
    "pays_en": "Côte d'Ivoire"
  },
  {
    "id": 111,
    "iso1": "JM",
    "pays_fr": "Jamaïque",
    "pays_en": "Jamaica"
  },
  {
    "id": 112,
    "iso1": "JP",
    "pays_fr": "Japon",
    "pays_en": "Japan"
  },
  {
    "id": 113,
    "iso1": "KZ",
    "pays_fr": "Kazakhstan",
    "pays_en": "Kazakhstan"
  },
  {
    "id": 114,
    "iso1": "JO",
    "pays_fr": "Jordanie",
    "pays_en": "Jordan"
  },
  {
    "id": 115,
    "iso1": "KE",
    "pays_fr": "Kenya",
    "pays_en": "Kenya"
  },
  {
    "id": 116,
    "iso1": "KP",
    "pays_fr": "Corée du Nord",
    "pays_en": "Democratic People's Republic of Korea"
  },
  {
    "id": 117,
    "iso1": "KR",
    "pays_fr": "Corée du Sud",
    "pays_en": "Republic of Korea"
  },
  {
    "id": 118,
    "iso1": "KW",
    "pays_fr": "Koweït",
    "pays_en": "Kuwait"
  },
  {
    "id": 119,
    "iso1": "KG",
    "pays_fr": "Kirghizistan",
    "pays_en": "Kyrgyzstan"
  },
  {
    "id": 120,
    "iso1": "LA",
    "pays_fr": "République Démocratique Populaire Lao",
    "pays_en": "Lao People's Democratic Republic"
  },
  {
    "id": 121,
    "iso1": "LB",
    "pays_fr": "Liban",
    "pays_en": "Lebanon"
  },
  {
    "id": 122,
    "iso1": "LS",
    "pays_fr": "Lesotho",
    "pays_en": "Lesotho"
  },
  {
    "id": 123,
    "iso1": "LV",
    "pays_fr": "Lettonie",
    "pays_en": "Latvia"
  },
  {
    "id": 124,
    "iso1": "LR",
    "pays_fr": "Libéria",
    "pays_en": "Liberia"
  },
  {
    "id": 125,
    "iso1": "LY",
    "pays_fr": "Jamahiriya Arabe Libyenne",
    "pays_en": "Libyan Arab Jamahiriya"
  },
  {
    "id": 126,
    "iso1": "LI",
    "pays_fr": "Liechtenstein",
    "pays_en": "Liechtenstein"
  },
  {
    "id": 127,
    "iso1": "LT",
    "pays_fr": "Lituanie",
    "pays_en": "Lithuania"
  },
  {
    "id": 128,
    "iso1": "LU",
    "pays_fr": "Luxembourg",
    "pays_en": "Luxembourg"
  },
  {
    "id": 129,
    "iso1": "MO",
    "pays_fr": "Macao",
    "pays_en": "Macao"
  },
  {
    "id": 130,
    "iso1": "MG",
    "pays_fr": "Madagascar",
    "pays_en": "Madagascar"
  },
  {
    "id": 131,
    "iso1": "MW",
    "pays_fr": "Malawi",
    "pays_en": "Malawi"
  },
  {
    "id": 132,
    "iso1": "MY",
    "pays_fr": "Malaisie",
    "pays_en": "Malaysia"
  },
  {
    "id": 133,
    "iso1": "MV",
    "pays_fr": "Maldives",
    "pays_en": "Maldives"
  },
  {
    "id": 134,
    "iso1": "ML",
    "pays_fr": "Mali",
    "pays_en": "Mali"
  },
  {
    "id": 135,
    "iso1": "MT",
    "pays_fr": "Malte",
    "pays_en": "Malta"
  },
  {
    "id": 136,
    "iso1": "MQ",
    "pays_fr": "Martinique",
    "pays_en": "Martinique"
  },
  {
    "id": 137,
    "iso1": "MR",
    "pays_fr": "Mauritanie",
    "pays_en": "Mauritania"
  },
  {
    "id": 138,
    "iso1": "MU",
    "pays_fr": "Maurice",
    "pays_en": "Mauritius"
  },
  {
    "id": 139,
    "iso1": "MX",
    "pays_fr": "Mexique",
    "pays_en": "Mexico"
  },
  {
    "id": 140,
    "iso1": "MC",
    "pays_fr": "Monaco",
    "pays_en": "Monaco"
  },
  {
    "id": 141,
    "iso1": "MN",
    "pays_fr": "Mongolie",
    "pays_en": "Mongolia"
  },
  {
    "id": 142,
    "iso1": "MD",
    "pays_fr": "République de Moldova",
    "pays_en": "Republic of Moldova"
  },
  {
    "id": 143,
    "iso1": "MS",
    "pays_fr": "Montserrat",
    "pays_en": "Montserrat"
  },
  {
    "id": 144,
    "iso1": "MA",
    "pays_fr": "Maroc",
    "pays_en": "Morocco"
  },
  {
    "id": 145,
    "iso1": "MZ",
    "pays_fr": "Mozambique",
    "pays_en": "Mozambique"
  },
  {
    "id": 146,
    "iso1": "OM",
    "pays_fr": "Oman",
    "pays_en": "Oman"
  },
  {
    "id": 147,
    "iso1": "NA",
    "pays_fr": "Namibie",
    "pays_en": "Namibia"
  },
  {
    "id": 148,
    "iso1": "NR",
    "pays_fr": "Nauru",
    "pays_en": "Nauru"
  },
  {
    "id": 149,
    "iso1": "NP",
    "pays_fr": "Népal",
    "pays_en": "Nepal"
  },
  {
    "id": 150,
    "iso1": "NL",
    "pays_fr": "Pays-Bas",
    "pays_en": "Netherlands"
  },
  {
    "id": 151,
    "iso1": "AN",
    "pays_fr": "Antilles Néerlandaises",
    "pays_en": "Netherlands Antilles"
  },
  {
    "id": 152,
    "iso1": "AW",
    "pays_fr": "Aruba",
    "pays_en": "Aruba"
  },
  {
    "id": 153,
    "iso1": "NC",
    "pays_fr": "Nouvelle-Calédonie",
    "pays_en": "New Caledonia"
  },
  {
    "id": 154,
    "iso1": "VU",
    "pays_fr": "Vanuatu",
    "pays_en": "Vanuatu"
  },
  {
    "id": 155,
    "iso1": "NZ",
    "pays_fr": "Nouvelle-Zélande",
    "pays_en": "New Zealand"
  },
  {
    "id": 156,
    "iso1": "NI",
    "pays_fr": "Nicaragua",
    "pays_en": "Nicaragua"
  },
  {
    "id": 157,
    "iso1": "NE",
    "pays_fr": "Niger",
    "pays_en": "Niger"
  },
  {
    "id": 158,
    "iso1": "NG",
    "pays_fr": "Nigéria",
    "pays_en": "Nigeria"
  },
  {
    "id": 159,
    "iso1": "NU",
    "pays_fr": "Niué",
    "pays_en": "Niue"
  },
  {
    "id": 160,
    "iso1": "NF",
    "pays_fr": "Île Norfolk",
    "pays_en": "Norfolk Island"
  },
  {
    "id": 161,
    "iso1": "NO",
    "pays_fr": "Norvège",
    "pays_en": "Norway"
  },
  {
    "id": 162,
    "iso1": "MP",
    "pays_fr": "Îles Mariannes du Nord",
    "pays_en": "Northern Mariana Islands"
  },
  {
    "id": 163,
    "iso1": "UM",
    "pays_fr": "Îles Mineures Éloignées des États-Unis",
    "pays_en": "United States Minor Outlying Islands"
  },
  {
    "id": 164,
    "iso1": "FM",
    "pays_fr": "États Fédérés de Micronésie",
    "pays_en": "Federated States of Micronesia"
  },
  {
    "id": 165,
    "iso1": "MH",
    "pays_fr": "Îles Marshall",
    "pays_en": "Marshall Islands"
  },
  {
    "id": 166,
    "iso1": "PW",
    "pays_fr": "Palaos",
    "pays_en": "Palau"
  },
  {
    "id": 167,
    "iso1": "PK",
    "pays_fr": "Pakistan",
    "pays_en": "Pakistan"
  },
  {
    "id": 168,
    "iso1": "PA",
    "pays_fr": "Panama",
    "pays_en": "Panama"
  },
  {
    "id": 169,
    "iso1": "PG",
    "pays_fr": "Papouasie-Nouvelle-Guinée",
    "pays_en": "Papua New Guinea"
  },
  {
    "id": 170,
    "iso1": "PY",
    "pays_fr": "Paraguay",
    "pays_en": "Paraguay"
  },
  {
    "id": 171,
    "iso1": "PE",
    "pays_fr": "Pérou",
    "pays_en": "Peru"
  },
  {
    "id": 172,
    "iso1": "PH",
    "pays_fr": "Philippines",
    "pays_en": "Philippines"
  },
  {
    "id": 173,
    "iso1": "PN",
    "pays_fr": "Pitcairn",
    "pays_en": "Pitcairn"
  },
  {
    "id": 174,
    "iso1": "PL",
    "pays_fr": "Pologne",
    "pays_en": "Poland"
  },
  {
    "id": 175,
    "iso1": "PT",
    "pays_fr": "Portugal",
    "pays_en": "Portugal"
  },
  {
    "id": 176,
    "iso1": "GW",
    "pays_fr": "Guinée-Bissau",
    "pays_en": "Guinea-Bissau"
  },
  {
    "id": 177,
    "iso1": "TL",
    "pays_fr": "Timor-Leste",
    "pays_en": "Timor-Leste"
  },
  {
    "id": 178,
    "iso1": "PR",
    "pays_fr": "Porto Rico",
    "pays_en": "Puerto Rico"
  },
  {
    "id": 179,
    "iso1": "QA",
    "pays_fr": "Qatar",
    "pays_en": "Qatar"
  },
  {
    "id": 180,
    "iso1": "RE",
    "pays_fr": "Réunion",
    "pays_en": "Réunion"
  },
  {
    "id": 181,
    "iso1": "RO",
    "pays_fr": "Roumanie",
    "pays_en": "Romania"
  },
  {
    "id": 182,
    "iso1": "RU",
    "pays_fr": "Russie",
    "pays_en": "Russian Federation"
  },
  {
    "id": 183,
    "iso1": "RW",
    "pays_fr": "Rwanda",
    "pays_en": "Rwanda"
  },
  {
    "id": 184,
    "iso1": "SH",
    "pays_fr": "Sainte-Hélène",
    "pays_en": "Saint Helena"
  },
  {
    "id": 185,
    "iso1": "KN",
    "pays_fr": "Saint-Kitts-et-Nevis",
    "pays_en": "Saint Kitts and Nevis"
  },
  {
    "id": 186,
    "iso1": "AI",
    "pays_fr": "Anguilla",
    "pays_en": "Anguilla"
  },
  {
    "id": 187,
    "iso1": "LC",
    "pays_fr": "Sainte-Lucie",
    "pays_en": "Saint Lucia"
  },
  {
    "id": 188,
    "iso1": "PM",
    "pays_fr": "Saint-Pierre-et-Miquelon",
    "pays_en": "Saint-Pierre and Miquelon"
  },
  {
    "id": 189,
    "iso1": "VC",
    "pays_fr": "Saint-Vincent-et-les Grenadines",
    "pays_en": "Saint Vincent and the Grenadines"
  },
  {
    "id": 190,
    "iso1": "SM",
    "pays_fr": "Saint-Marin",
    "pays_en": "San Marino"
  },
  {
    "id": 191,
    "iso1": "ST",
    "pays_fr": "Sao Tomé-et-Principe",
    "pays_en": "Sao Tome and Principe"
  },
  {
    "id": 192,
    "iso1": "SA",
    "pays_fr": "Arabie Saoudite",
    "pays_en": "Saudi Arabia"
  },
  {
    "id": 193,
    "iso1": "SN",
    "pays_fr": "Sénégal",
    "pays_en": "Senegal"
  },
  {
    "id": 194,
    "iso1": "SC",
    "pays_fr": "Seychelles",
    "pays_en": "Seychelles"
  },
  {
    "id": 195,
    "iso1": "SL",
    "pays_fr": "Sierra Leone",
    "pays_en": "Sierra Leone"
  },
  {
    "id": 196,
    "iso1": "SG",
    "pays_fr": "Singapour",
    "pays_en": "Singapore"
  },
  {
    "id": 197,
    "iso1": "SK",
    "pays_fr": "Slovaquie",
    "pays_en": "Slovakia"
  },
  {
    "id": 198,
    "iso1": "VN",
    "pays_fr": "Viet Nam",
    "pays_en": "Vietnam"
  },
  {
    "id": 199,
    "iso1": "SI",
    "pays_fr": "Slovénie",
    "pays_en": "Slovenia"
  },
  {
    "id": 200,
    "iso1": "SO",
    "pays_fr": "Somalie",
    "pays_en": "Somalia"
  },
  {
    "id": 201,
    "iso1": "ZA",
    "pays_fr": "Afrique du Sud",
    "pays_en": "South Africa"
  },
  {
    "id": 202,
    "iso1": "ZW",
    "pays_fr": "Zimbabwe",
    "pays_en": "Zimbabwe"
  },
  {
    "id": 203,
    "iso1": "ES",
    "pays_fr": "Espagne",
    "pays_en": "Spain"
  },
  {
    "id": 204,
    "iso1": "EH",
    "pays_fr": "Sahara Occidental",
    "pays_en": "Western Sahara"
  },
  {
    "id": 205,
    "iso1": "SD",
    "pays_fr": "Soudan",
    "pays_en": "Sudan"
  },
  {
    "id": 206,
    "iso1": "SR",
    "pays_fr": "Suriname",
    "pays_en": "Suriname"
  },
  {
    "id": 207,
    "iso1": "SJ",
    "pays_fr": "Svalbard etÎle Jan Mayen",
    "pays_en": "Svalbard and Jan Mayen"
  },
  {
    "id": 208,
    "iso1": "SZ",
    "pays_fr": "Swaziland",
    "pays_en": "Swaziland"
  },
  {
    "id": 209,
    "iso1": "SE",
    "pays_fr": "Suède",
    "pays_en": "Sweden"
  },
  {
    "id": 210,
    "iso1": "CH",
    "pays_fr": "Suisse",
    "pays_en": "Switzerland"
  },
  {
    "id": 211,
    "iso1": "SY",
    "pays_fr": "République Arabe Syrienne",
    "pays_en": "Syrian Arab Republic"
  },
  {
    "id": 212,
    "iso1": "TJ",
    "pays_fr": "Tadjikistan",
    "pays_en": "Tajikistan"
  },
  {
    "id": 213,
    "iso1": "TH",
    "pays_fr": "Thaïlande",
    "pays_en": "Thailand"
  },
  {
    "id": 214,
    "iso1": "TG",
    "pays_fr": "Togo",
    "pays_en": "Togo"
  },
  {
    "id": 215,
    "iso1": "TK",
    "pays_fr": "Tokelau",
    "pays_en": "Tokelau"
  },
  {
    "id": 216,
    "iso1": "TO",
    "pays_fr": "Tonga",
    "pays_en": "Tonga"
  },
  {
    "id": 217,
    "iso1": "TT",
    "pays_fr": "Trinité-et-Tobago",
    "pays_en": "Trinidad and Tobago"
  },
  {
    "id": 218,
    "iso1": "AE",
    "pays_fr": "Émirats Arabes Unis",
    "pays_en": "United Arab Emirates"
  },
  {
    "id": 219,
    "iso1": "TN",
    "pays_fr": "Tunisie",
    "pays_en": "Tunisia"
  },
  {
    "id": 220,
    "iso1": "TR",
    "pays_fr": "Turquie",
    "pays_en": "Turkey"
  },
  {
    "id": 221,
    "iso1": "TM",
    "pays_fr": "Turkménistan",
    "pays_en": "Turkmenistan"
  },
  {
    "id": 222,
    "iso1": "TC",
    "pays_fr": "Îles Turks et Caïques",
    "pays_en": "Turks and Caicos Islands"
  },
  {
    "id": 223,
    "iso1": "TV",
    "pays_fr": "Tuvalu",
    "pays_en": "Tuvalu"
  },
  {
    "id": 224,
    "iso1": "UG",
    "pays_fr": "Ouganda",
    "pays_en": "Uganda"
  },
  {
    "id": 225,
    "iso1": "UA",
    "pays_fr": "Ukraine",
    "pays_en": "Ukraine"
  },
  {
    "id": 226,
    "iso1": "MK",
    "pays_fr": "L'ex-République Yougoslave de Macédoine",
    "pays_en": "The Former Yugoslav Republic of Macedonia"
  },
  {
    "id": 227,
    "iso1": "EG",
    "pays_fr": "Égypte",
    "pays_en": "Egypt"
  },
  {
    "id": 228,
    "iso1": "GB",
    "pays_fr": "Royaume-Uni",
    "pays_en": "United Kingdom"
  },
  {
    "id": 229,
    "iso1": "IM",
    "pays_fr": "Île de Man",
    "pays_en": "Isle of Man"
  },
  {
    "id": 230,
    "iso1": "TZ",
    "pays_fr": "République-Unie de Tanzanie",
    "pays_en": "United Republic Of Tanzania"
  },
  {
    "id": 231,
    "iso1": "US",
    "pays_fr": "États-Unis",
    "pays_en": "United States"
  },
  {
    "id": 232,
    "iso1": "VI",
    "pays_fr": "Îles Vierges des États-Unis",
    "pays_en": "U.S. Virgin Islands"
  },
  {
    "id": 233,
    "iso1": "BF",
    "pays_fr": "Burkina Faso",
    "pays_en": "Burkina Faso"
  },
  {
    "id": 234,
    "iso1": "UY",
    "pays_fr": "Uruguay",
    "pays_en": "Uruguay"
  },
  {
    "id": 235,
    "iso1": "UZ",
    "pays_fr": "Ouzbékistan",
    "pays_en": "Uzbekistan"
  },
  {
    "id": 236,
    "iso1": "VE",
    "pays_fr": "Venezuela",
    "pays_en": "Venezuela"
  },
  {
    "id": 237,
    "iso1": "WF",
    "pays_fr": "Wallis et Futuna",
    "pays_en": "Wallis and Futuna"
  },
  {
    "id": 238,
    "iso1": "WS",
    "pays_fr": "Samoa",
    "pays_en": "Samoa"
  },
  {
    "id": 239,
    "iso1": "YE",
    "pays_fr": "Yémen",
    "pays_en": "Yemen"
  },
  {
    "id": 240,
    "iso1": "CS",
    "pays_fr": "Serbie Monténégro",
    "pays_en": "Serbia and Montenegro"
  },
  {
    "id": 241,
    "iso1": "ZM",
    "pays_fr": "Zambie",
    "pays_en": "Zambia"
  }
]